multiauth/__init__.py
multiauth/__main__.py
multiauth/cli/__init__.py
multiauth/cli/cli.py
multiauth/cli/commands/__init__.py
multiauth/cli/commands/init.py
multiauth/cli/commands/lint.py
multiauth/cli/commands/parser.py
multiauth/cli/commands/validate.py
multiauth/cli/load.py
multiauth/configuration.py
multiauth/exceptions.py
multiauth/helpers/__init__.py
multiauth/helpers/base_model.py
multiauth/helpers/logger.py
multiauth/helpers/slug.py
multiauth/lib/__init__.py
multiauth/lib/audit/__init__.py
multiauth/lib/audit/events/__init__.py
multiauth/lib/audit/events/base.py
multiauth/lib/audit/events/events.py
multiauth/lib/audit/reporters/__init__.py
multiauth/lib/audit/reporters/base.py
multiauth/lib/audit/reporters/console.py
multiauth/lib/audit/reporters/json.py
multiauth/lib/audit/reporters/raw.py
multiauth/lib/entities.py
multiauth/lib/extraction.py
multiauth/lib/http_core/__init__.py
multiauth/lib/http_core/curl.py
multiauth/lib/http_core/curl_test.py
multiauth/lib/http_core/entities.py
multiauth/lib/http_core/entities_test.py
multiauth/lib/http_core/mergers.py
multiauth/lib/http_core/parsers.py
multiauth/lib/http_core/request.py
multiauth/lib/injection.py
multiauth/lib/presets/__init__.py
multiauth/lib/presets/base.py
multiauth/lib/presets/basic.py
multiauth/lib/presets/cognito_userpass.py
multiauth/lib/presets/curl.py
multiauth/lib/presets/digest.py
multiauth/lib/presets/graphql.py
multiauth/lib/presets/headers.py
multiauth/lib/presets/http.py
multiauth/lib/presets/oauth_client_credentials.py
multiauth/lib/presets/oauth_userpass.py
multiauth/lib/presets/webdriver.py
multiauth/lib/procedure.py
multiauth/lib/runners/__init__.py
multiauth/lib/runners/base.py
multiauth/lib/runners/digest.py
multiauth/lib/runners/http.py
multiauth/lib/runners/webdriver/__init__.py
multiauth/lib/runners/webdriver/configuration.py
multiauth/lib/runners/webdriver/driver.py
multiauth/lib/runners/webdriver/extractors.py
multiauth/lib/runners/webdriver/handler.py
py_multiauth-3.0.9.dist-info/LICENSE
py_multiauth-3.0.9.dist-info/METADATA
py_multiauth-3.0.9.dist-info/WHEEL
py_multiauth-3.0.9.dist-info/entry_points.txt
py_multiauth-3.0.9.dist-info/RECORD
