Metadata-Version: 2.1
Name: py-multiauth
Version: 3.0.9
Summary: Python package to interact with multiple authentication services
Home-page: https://escape.tech/
License: MIT
Author: Escape Technologies SAS
Author-email: ping@escape.tech
Maintainer: Antoine Carossio
Maintainer-email: antoine@escape.tech
Requires-Python: >=3.11,<4.0
Classifier: License :: OSI Approved :: MIT License
Classifier: Programming Language :: Python :: 3
Classifier: Programming Language :: Python :: 3.11
Classifier: Programming Language :: Python :: 3.12
Requires-Dist: deepmerge (>=1.1.1,<2.0.0)
Requires-Dist: httpx[http2] (>=0.26.0,<0.27.0)
Requires-Dist: pydantic (>=2.5.3,<3.0.0)
Requires-Dist: selenium (>=4.16.0,<5.0.0)
Requires-Dist: selenium-wire (>=5.1.0,<6.0.0)
Project-URL: Bug Tracker, https://github.com/Escape-Technologies/py-multiauth/issues
Project-URL: Repository, https://github.com/Escape-Technologies/py-multiauth
